pancax/__init__.py
pancax/history_writer.py
pancax/logging.py
pancax/post_processor.py
pancax/timer.py
pancax/trainer.py
pancax/utils.py
pancax/bcs/__init__.py
pancax/bcs/dirichlet_bc.py
pancax/bcs/distance_functions.py
pancax/bcs/neumann_bc.py
pancax/bvps/__init__.py
pancax/bvps/biaxial_tension.py
pancax/bvps/simple_shear.py
pancax/bvps/uniaxial_tension.py
pancax/cli/__init__.py
pancax/cli/cli.py
pancax/constitutive_models/__init__.py
pancax/constitutive_models/base.py
pancax/constitutive_models/properties.py
pancax/constitutive_models/mechanics/__init__.py
pancax/constitutive_models/mechanics/base.py
pancax/constitutive_models/mechanics/hyperelasticity/__init__.py
pancax/constitutive_models/mechanics/hyperelasticity/blatz_ko.py
pancax/constitutive_models/mechanics/hyperelasticity/gent.py
pancax/constitutive_models/mechanics/hyperelasticity/hencky.py
pancax/constitutive_models/mechanics/hyperelasticity/neohookean.py
pancax/constitutive_models/mechanics/hyperelasticity/swanson.py
pancax/constitutive_models/mechanics/hyperviscoelasticity/__init__.py
pancax/constitutive_models/mechanics/hyperviscoelasticity/base.py
pancax/constitutive_models/mechanics/hyperviscoelasticity/simple_fefv.py
pancax/data/__init__.py
pancax/data/full_field_data.py
pancax/data/global_data.py
pancax/domains/__init__.py
pancax/domains/base.py
pancax/domains/collocation_domain.py
pancax/domains/delta_pinn_domain.py
pancax/domains/variational_domain.py
pancax/fem/__init__.py
pancax/fem/dof_manager.py
pancax/fem/function_space.py
pancax/fem/mesh.py
pancax/fem/quadrature_rules.py
pancax/fem/read_exodus_mesh.py
pancax/fem/sparse_matrix_assembler.py
pancax/fem/surface.py
pancax/fem/traction_bc.py
pancax/fem/elements/__init__.py
pancax/fem/elements/base_element.py
pancax/fem/elements/hex8_element.py
pancax/fem/elements/line_element.py
pancax/fem/elements/quad4_element.py
pancax/fem/elements/quad9_element.py
pancax/fem/elements/simplex_tri_element.py
pancax/fem/elements/tet10_element.py
pancax-0.0.14.dist-info/METADATA
pancax-0.0.14.dist-info/WHEEL
pancax-0.0.14.dist-info/entry_points.txt
pancax-0.0.14.dist-info/licenses/LICENSE
pancax-0.0.14.dist-info/RECORD
