Metadata-Version: 2.4
Name: pancax
Version: 0.0.14
Author: Craig M. Hamel, email = <chamel@sandia.gov>
License-File: LICENSE
Requires-Dist: matplotlib
Requires-Dist: meshio
Requires-Dist: netcdf4
Requires-Dist: pandas
Requires-Dist: scipy
Requires-Dist: vtk
Provides-Extra: cpu
Requires-Dist: chex; extra == 'cpu'
Requires-Dist: equinox==0.13; extra == 'cpu'
Requires-Dist: jax==0.6.2; extra == 'cpu'
Requires-Dist: jaxtyping; extra == 'cpu'
Requires-Dist: optax; extra == 'cpu'
Provides-Extra: cuda
Requires-Dist: chex; extra == 'cuda'
Requires-Dist: equinox==0.13; extra == 'cuda'
Requires-Dist: jax[cuda12]==0.6.2; extra == 'cuda'
Requires-Dist: jaxtyping; extra == 'cuda'
Requires-Dist: optax; extra == 'cuda'
Provides-Extra: dev
Requires-Dist: flake8; extra == 'dev'
Requires-Dist: pytest; extra == 'dev'
Requires-Dist: pytest-cov; extra == 'dev'
Requires-Dist: pytest-xdist; extra == 'dev'
Requires-Dist: sphinx; extra == 'dev'
Requires-Dist: sphinx-copybutton; extra == 'dev'
Requires-Dist: sphinx-rtd-theme; extra == 'dev'
Requires-Dist: sphinxcontrib-bibtex; extra == 'dev'
Requires-Dist: sphinxcontrib-napoleon; extra == 'dev'
Provides-Extra: rocm
Requires-Dist: chex; extra == 'rocm'
Requires-Dist: equinox==0.12.1; extra == 'rocm'
Requires-Dist: jax[rocm]==0.5.0; extra == 'rocm'
Requires-Dist: jaxtyping; extra == 'rocm'
Requires-Dist: optax; extra == 'rocm'
Provides-Extra: viz
Requires-Dist: pyvista; extra == 'viz'
